mantrapy/__init__.py
mantrapy/client/__init__.py
mantrapy/client/client.py
mantrapy/constants/__init__.py
mantrapy/constants/constants.py
mantrapy/proto/__init__.py
mantrapy/proto/cosmos/__init__.py
mantrapy/proto/cosmos/auth/__init__.py
mantrapy/proto/cosmos/auth/v1beta1/__init__.py
mantrapy/proto/cosmos/auth/v1beta1/auth_pb2.py
mantrapy/proto/cosmos/auth/v1beta1/auth_pb2_grpc.py
mantrapy/proto/cosmos/auth/v1beta1/genesis_pb2.py
mantrapy/proto/cosmos/auth/v1beta1/genesis_pb2_grpc.py
mantrapy/proto/cosmos/auth/v1beta1/query_pb2.py
mantrapy/proto/cosmos/auth/v1beta1/query_pb2_grpc.py
mantrapy/proto/cosmos/authz/__init__.py
mantrapy/proto/cosmos/authz/v1beta1/__init__.py
mantrapy/proto/cosmos/authz/v1beta1/authz_pb2.py
mantrapy/proto/cosmos/authz/v1beta1/authz_pb2_grpc.py
mantrapy/proto/cosmos/authz/v1beta1/event_pb2.py
mantrapy/proto/cosmos/authz/v1beta1/event_pb2_grpc.py
mantrapy/proto/cosmos/authz/v1beta1/genesis_pb2.py
mantrapy/proto/cosmos/authz/v1beta1/genesis_pb2_grpc.py
mantrapy/proto/cosmos/authz/v1beta1/query_pb2.py
mantrapy/proto/cosmos/authz/v1beta1/query_pb2_grpc.py
mantrapy/proto/cosmos/authz/v1beta1/tx_pb2.py
mantrapy/proto/cosmos/authz/v1beta1/tx_pb2_grpc.py
mantrapy/proto/cosmos/bank/__init__.py
mantrapy/proto/cosmos/bank/v1beta1/__init__.py
mantrapy/proto/cosmos/bank/v1beta1/authz_pb2.py
mantrapy/proto/cosmos/bank/v1beta1/authz_pb2_grpc.py
mantrapy/proto/cosmos/bank/v1beta1/bank_pb2.py
mantrapy/proto/cosmos/bank/v1beta1/bank_pb2_grpc.py
mantrapy/proto/cosmos/bank/v1beta1/genesis_pb2.py
mantrapy/proto/cosmos/bank/v1beta1/genesis_pb2_grpc.py
mantrapy/proto/cosmos/bank/v1beta1/query_pb2.py
mantrapy/proto/cosmos/bank/v1beta1/query_pb2_grpc.py
mantrapy/proto/cosmos/bank/v1beta1/tx_pb2.py
mantrapy/proto/cosmos/bank/v1beta1/tx_pb2_grpc.py
mantrapy/proto/cosmos/base/__init__.py
mantrapy/proto/cosmos/base/abci/__init__.py
mantrapy/proto/cosmos/base/abci/v1beta1/__init__.py
mantrapy/proto/cosmos/base/abci/v1beta1/abci_pb2.py
mantrapy-0.0.2.dist-info/METADATA
mantrapy-0.0.2.dist-info/WHEEL
mantrapy-0.0.2.dist-info/top_level.txt
mantrapy-0.0.2.dist-info/RECORD
